foxy437lib/__init__.py
foxy437lib/main.py
foxy437lib-1.5.0.0.dist-info/METADATA
foxy437lib-1.5.0.0.dist-info/WHEEL
foxy437lib-1.5.0.0.dist-info/top_level.txt
foxy437lib-1.5.0.0.dist-info/RECORD
