Metadata-Version: 2.1
Name: foxy437lib
Version: 1.5.0.0
Summary: ???
Author: ???
Classifier: Programming Language :: Python :: 3
Classifier: License :: OSI Approved :: MIT License
Classifier: Operating System :: OS Independent
Requires-Python: >=3.6
Requires-Dist: telethon
